jps_nextflow_utils/__init__.py
jps_nextflow_utils/auditor.py
jps_nextflow_utils/batch.py
jps_nextflow_utils/cli.py
jps_nextflow_utils/diff.py
jps_nextflow_utils/discovery.py
jps_nextflow_utils/log_parser.py
jps_nextflow_utils/models.py
jps_nextflow_utils/reporters.py
jps_nextflow_utils/rules.py
jps_nextflow_utils/trace_parser.py
jps_nextflow_utils-0.2.0.dist-info/licenses/LICENSE
jps_nextflow_utils-0.2.0.dist-info/METADATA
jps_nextflow_utils-0.2.0.dist-info/WHEEL
jps_nextflow_utils-0.2.0.dist-info/entry_points.txt
jps_nextflow_utils-0.2.0.dist-info/top_level.txt
jps_nextflow_utils-0.2.0.dist-info/RECORD
