Metadata-Version: 2.4
Name: jps-nextflow-utils
Version: 0.2.0
Summary: Offline analysis of Nextflow run artifacts - audit, report, and compare workflow runs
Author-email: Jaideep Sundaram <jai.python3@gmail.com>
License: MIT
Project-URL: Homepage, https://github.com/jai-python3/jps-nextflow-utils
Project-URL: Repository, https://github.com/jai-python3/jps-nextflow-utils
Project-URL: Issues, https://github.com/jai-python3/jps-nextflow-utils/issues
Keywords: nextflow,workflow,audit,analysis,bioinformatics,pipeline
Classifier: Programming Language :: Python :: 3
Classifier: Programming Language :: Python :: 3.10
Classifier: Programming Language :: Python :: 3.11
Classifier: Programming Language :: Python :: 3.12
Classifier: License :: OSI Approved :: MIT License
Classifier: Operating System :: OS Independent
Classifier: Development Status :: 4 - Beta
Classifier: Intended Audience :: Science/Research
Classifier: Intended Audience :: Developers
Classifier: Topic :: Scientific/Engineering :: Bio-Informatics
Requires-Python: >=3.10
License-File: LICENSE
Requires-Dist: typer>=0.12.3
Requires-Dist: pyyaml>=6.0.0
Provides-Extra: test
Requires-Dist: pytest>=8.0.0; extra == "test"
Provides-Extra: dev
Requires-Dist: flake8>=7.0.0; extra == "dev"
Requires-Dist: black>=24.0.0; extra == "dev"
Requires-Dist: build>=1.2.1; extra == "dev"
Requires-Dist: twine>=5.0.0; extra == "dev"
Requires-Dist: pytest>=8.0.0; extra == "dev"
Requires-Dist: pytest-cov>=5.0.0; extra == "dev"
Requires-Dist: isort>=5.13.0; extra == "dev"
Requires-Dist: codecov>=2.1.13; extra == "dev"
Requires-Dist: autoflake>=2.3.1; extra == "dev"
Requires-Dist: pre-commit>=3.8.0; extra == "dev"
Requires-Dist: bandit>=1.7.9; extra == "dev"
Requires-Dist: vulture>=2.11; extra == "dev"
Requires-Dist: flynt>=1.0.1; extra == "dev"
Requires-Dist: pydocstyle>=6.3.0; extra == "dev"
Requires-Dist: darglint>=1.8.1; extra == "dev"
Requires-Dist: mypy>=1.12.1; extra == "dev"
Requires-Dist: bump-my-version>=1.0.1; extra == "dev"
Requires-Dist: git-changelog>=2.7.0; extra == "dev"
Dynamic: license-file
